odoo/addons/l10n_it_delivery_note_rma/README.rst
odoo/addons/l10n_it_delivery_note_rma/__init__.py
odoo/addons/l10n_it_delivery_note_rma/__manifest__.py
odoo/addons/l10n_it_delivery_note_rma/controllers/__init__.py
odoo/addons/l10n_it_delivery_note_rma/controllers/delivery_note_portal.py
odoo/addons/l10n_it_delivery_note_rma/controllers/rma_portal.py
odoo/addons/l10n_it_delivery_note_rma/i18n/it.po
odoo/addons/l10n_it_delivery_note_rma/i18n/l10n_it_delivery_note_rma.pot
odoo/addons/l10n_it_delivery_note_rma/models/__init__.py
odoo/addons/l10n_it_delivery_note_rma/models/rma.py
odoo/addons/l10n_it_delivery_note_rma/models/stock_delivery_note.py
odoo/addons/l10n_it_delivery_note_rma/models/stock_move.py
odoo/addons/l10n_it_delivery_note_rma/readme/CONTRIBUTORS.rst
odoo/addons/l10n_it_delivery_note_rma/readme/DESCRIPTION.rst
odoo/addons/l10n_it_delivery_note_rma/readme/USAGE.rst
odoo/addons/l10n_it_delivery_note_rma/security/ir.model.access.csv
odoo/addons/l10n_it_delivery_note_rma/static/description/icon.png
odoo/addons/l10n_it_delivery_note_rma/static/description/index.html
odoo/addons/l10n_it_delivery_note_rma/static/src/js/rma_portal_form.js
odoo/addons/l10n_it_delivery_note_rma/tests/__init__.py
odoo/addons/l10n_it_delivery_note_rma/tests/delivery_note_common.py
odoo/addons/l10n_it_delivery_note_rma/tests/test_delivery_note_rma.py
odoo/addons/l10n_it_delivery_note_rma/tests/test_delivery_note_rma_portal.py
odoo/addons/l10n_it_delivery_note_rma/views/assets.xml
odoo/addons/l10n_it_delivery_note_rma/views/delivery_portal_template.xml
odoo/addons/l10n_it_delivery_note_rma/views/delivery_views.xml
odoo/addons/l10n_it_delivery_note_rma/views/rma_views.xml
odoo/addons/l10n_it_delivery_note_rma/wizard/__init__.py
odoo/addons/l10n_it_delivery_note_rma/wizard/stock_delivery_note_rma_wizard.py
odoo/addons/l10n_it_delivery_note_rma/wizard/stock_delivery_note_rma_wizard_views.xml
odoo14_addon_l10n_it_delivery_note_rma-14.0.1.1.0.dist-info/METADATA
odoo14_addon_l10n_it_delivery_note_rma-14.0.1.1.0.dist-info/WHEEL
odoo14_addon_l10n_it_delivery_note_rma-14.0.1.1.0.dist-info/top_level.txt
odoo14_addon_l10n_it_delivery_note_rma-14.0.1.1.0.dist-info/RECORD
